dtelbot/__init__.py
dtelbot-0.0.4.dist-info/LICENSE
dtelbot-0.0.4.dist-info/METADATA
dtelbot-0.0.4.dist-info/WHEEL
dtelbot-0.0.4.dist-info/top_level.txt
dtelbot-0.0.4.dist-info/RECORD
