Metadata-Version: 2.1
Name: dtelbot
Version: 0.0.4
Summary: Simple Telegram bot lib with regex checking and async features
Home-page: https://github.com/dalor
Author: dalor
Author-email: dalor@i.ua
License: UNKNOWN
Platform: UNKNOWN
Classifier: Programming Language :: Python :: 3
Classifier: License :: OSI Approved :: MIT License
Classifier: Operating System :: OS Independent
